bstpackage/__init__.py
bstpackage/__main__.py
bstpackage/generateBST.py
bstpackage-0.0.7.dist-info/LICENSE
bstpackage-0.0.7.dist-info/METADATA
bstpackage-0.0.7.dist-info/WHEEL
bstpackage-0.0.7.dist-info/entry_points.txt
bstpackage-0.0.7.dist-info/top_level.txt
bstpackage-0.0.7.dist-info/RECORD
