Metadata-Version: 2.1
Name: bstpackage
Version: 0.0.7
Summary: A package that helps manipulate and visualize binary search trees.
Author-email: Alex Xiang <qx501@nyu.edu>, Yimeng Duan <yd2107@nyu.edu>, Richard Fu <df1942@nyu.edu>
License: GNU GENERAL PUBLIC LICENSE
Project-URL: Homepage, https://github.com/software-students-fall2023/3-python-package-exercise-ayr
Project-URL: Repository, https://github.com/software-students-fall2023/3-python-package-exercise-ayr.git
Project-URL: Bug Tracker, https://github.com/software-students-fall2023/3-python-package-exercise-ayr/issues
Keywords: python,package,BST,visualization
Classifier: Programming Language :: Python :: 3
Classifier: Intended Audience :: Education
Classifier: License :: OSI Approved :: GNU General Public License v3 (GPLv3)
Classifier: Operating System :: OS Independent
Requires-Python: >=3.8
License-File: LICENSE
Provides-Extra: dev
Requires-Dist: pytest ; extra == 'dev'
